LosaUnideireccional/__init__.py
LosaUnideireccional/armaduralongitudinalnegativa.py
LosaUnideireccional/controlDeflexion.py
LosaUnideireccional/determinacion_de_Cargas.py
LosaUnideireccional/determinacionMomentos_Ultimos.py
losaunideireccional-0.1.2.dist-info/WHEEL
losaunideireccional-0.1.2.dist-info/METADATA
losaunideireccional-0.1.2.dist-info/RECORD
