Metadata-Version: 2.1
Name: losaunideireccional
Version: 0.1.2
Summary: Diseño de carga de losa alivianada
License: MIT
Author: Imanazco
Author-email: ivanna_ao97@outlook.es
Requires-Python: >=3.9,<4.0
Classifier: License :: OSI Approved :: MIT License
Classifier: Programming Language :: Python :: 3
Classifier: Programming Language :: Python :: 3.10
Classifier: Programming Language :: Python :: 3.9
Requires-Dist: click (>=8.1.3,<9.0.0)
